[
{"title": "Nike Air Max 270 React (Pop Art)", "price": "$150"},
{"title": "Nike Air Max 270 React (Geometric Abstract)", "price": "$150"},
{"title": "Nike Joyride CC3 Setter", "price": "$180"},
{"title": "Nike Joyride Optik", "price": "$180"},
{"title": "Nike Joyride Run Flyknit", "price": "$180"},
{"title": "Nike Joyride Run Flyknit", "price": "$180"},
{"title": "Nike Air Max 720 (OBJ)", "price": "$200"},
{"title": "NikeCourt Lite 2 Premium", "price": "$75"},
{"title": "Jordan Jumpman Classics", "price": "$90"},
{"title": "Nike", "price": "$40"},
{"title": "Nike Sportswear Tech Fleece", "price": "$60"},
{"title": "Nike Sportswear Tech Fleece", "price": "$80"},
{"title": "Nike", "price": "$100"},
{"title": "Nike", "price": "$165"},
{"title": "Air Jordan 4 Retro", "price": "$140"},
{"title": "Air Jordan 4 Retro SE", "price": "$200"},
{"title": "Jordan 4 Retro", "price": "$80"},
{"title": "Air Jordan 4 Retro", "price": "$60"},
{"title": "Zoom Freak 1", "price": "$120"},
{"title": "Freak 1", "price": "$100"},
{"title": "Nike Zoom Moc", "price": "$140"},
{"title": "Nike React Sertu", "price": "$150"},
{"title": "Nike React Ianga", "price": "$130"},
{"title": "Air Jordan 10 Retro", "price": "$190"}
]